{
  "data": {
    "md5": "57dc41a2e9a8edb5a62db77d47f4116e",
    "path": "gui/layout_presets/toolbar.layout",
    "root": {
      "children": [
        {
          "__OBJ_TYPE": "DefaultWindow",
          "children": [
            {
              "__OBJ_TYPE": "StaticImage",
              "anchor": {
                "VerticalAlignment": "Centre"
              },
              "id": {
                "value": "514d5896-9150-4d80-af35-661d3f0edd78"
              },
              "Image": {
                "asset": "asset/Texture/Gui/imagesets/main_ui.imageset",
                "imageset_key": "icon_setting",
                "selector": "asset/Texture/Gui/imagesets/main_ui.imageset"
              },
              "name": "settingBtn",
              "pos": {
                "UDim_X": {
                  "Offect": 10
                }
              },
              "size": {
                "UDim_X": {
                  "Offect": 48
                },
                "UDim_Y": {
                  "Offect": 48
                }
              }
            },
            {
              "__OBJ_TYPE": "StaticImage",
              "anchor": {
                "VerticalAlignment": "Centre"
              },
              "id": {
                "value": "49b67672-ce32-4d40-9fba-2ec57de8497d"
              },
              "Image": {
                "asset": "asset/Texture/Gui/imagesets/main_ui.imageset",
                "imageset_key": "icon_chat",
                "selector": "asset/Texture/Gui/imagesets/main_ui.imageset"
              },
              "name": "chatBtn",
              "pos": {
                "UDim_X": {
                  "Offect": 68
                }
              },
              "size": {
                "UDim_X": {
                  "Offect": 48
                },
                "UDim_Y": {
                  "Offect": 48
                }
              }
            },
            {
              "__OBJ_TYPE": "StaticImage",
              "anchor": {
                "VerticalAlignment": "Centre"
              },
              "id": {
                "value": "0ed9ea95-3f17-4d23-8241-4f126ed6ced5"
              },
              "Image": {
                "asset": "asset/Texture/Gui/imagesets/main_ui.imageset",
                "imageset_key": "icon_thrid_view",
                "selector": "asset/Texture/Gui/imagesets/main_ui.imageset"
              },
              "name": "viewBtn",
              "pos": {
                "UDim_X": {
                  "Offect": 126
                }
              },
              "size": {
                "UDim_X": {
                  "Offect": 48
                },
                "UDim_Y": {
                  "Offect": 48
                }
              }
            },
            {
              "__OBJ_TYPE": "StaticImage",
              "anchor": {
                "VerticalAlignment": "Centre"
              },
              "id": {
                "value": "6c7bf1e1-d550-40f2-b4ad-8255f0637561"
              },
              "Image": {
                "asset": "asset/Texture/Gui/imagesets/friend.imageset",
                "imageset_key": "icon_friends",
                "selector": "asset/Texture/Gui/imagesets/friend.imageset"
              },
              "name": "playerListBtn",
              "pos": {
                "UDim_X": {
                  "Offect": 186
                }
              },
              "size": {
                "UDim_X": {
                  "Offect": 48
                },
                "UDim_Y": {
                  "Offect": 48
                }
              }
            }
          ],
          "id": {
            "value": "cc08bb7f-dd83-4cf6-b834-beb20418e973"
          },
          "name": "SystemBtnLayout",
          "pos": {
            "UDim_X": {
              "Offect": 10
            }
          },
          "size": {
            "UDim_X": {
              "Offect": 184
            },
            "UDim_Y": {
              "Offect": 0,
              "Scale": 1
            }
          }
        },
        {
          "__OBJ_TYPE": "DefaultWindow",
          "anchor": {
            "VerticalAlignment": "Centre"
          },
          "children": [
            {
              "__OBJ_TYPE": "StaticImage",
              "Alpha": 0.5,
              "BackgroundColours": {
                "b": 0,
                "g": 0,
                "r": 0
              },
              "BackgroundEnabled": true,
              "id": {
                "value": "0fb2c70b-ef9c-4227-bed5-059fa0ec1292"
              },
              "Image": {
                "asset": "",
                "selector": ""
              },
              "name": "teamBg",
              "size": {
                "UDim_X": {
                  "Offect": 0,
                  "Scale": 1
                },
                "UDim_Y": {
                  "Offect": 0,
                  "Scale": 1
                }
              },
              "WindowTouchThroughMode": "MousePassThroughOpen"
            }
          ],
          "id": {
            "value": "dfa1607a-8971-4e00-b492-f6b153b80a5d"
          },
          "name": "TeamLayout",
          "pos": {
            "UDim_X": {
              "Offect": 240
            }
          },
          "size": {
            "UDim_X": {
              "Offect": 320
            },
            "UDim_Y": {
              "Offect": 48
            }
          },
          "Visible": false,
          "WindowTouchThroughMode": "MousePassThroughOpen"
        },
        {
          "__OBJ_TYPE": "DefaultWindow",
          "anchor": {
            "HorizontalAlignment": "Right",
            "VerticalAlignment": "Centre"
          },
          "children": [
            {
              "__OBJ_TYPE": "StaticImage",
              "id": {
                "value": "3f09846a-6ae1-4dea-be2d-37f616eb951c"
              },
              "Image": {
                "asset": "asset/Texture/Gui/imagesets/main_ui.imageset",
                "imageset_key": "toolbar_Countdown",
                "selector": "asset/Texture/Gui/imagesets/main_ui.imageset"
              },
              "name": "countDownBg",
              "size": {
                "UDim_X": {
                  "Offect": 0,
                  "Scale": 1
                },
                "UDim_Y": {
                  "Offect": 0,
                  "Scale": 1
                }
              },
              "WindowTouchThroughMode": "MousePassThroughOpen"
            },
            {
              "__OBJ_TYPE": "StaticText",
              "anchor": {
                "VerticalAlignment": "Centre"
              },
              "BorderWidth": 1,
              "Font_size": 16,
              "id": {
                "value": "41376550-4b3f-4d9b-871a-9258c204e278"
              },
              "name": "countDownText",
              "pos": {
                "UDim_X": {
                  "Offect": 40
                }
              },
              "size": {
                "UDim_X": {
                  "Offect": -45.79,
                  "Scale": 1
                },
                "UDim_Y": {
                  "Offect": -8.08,
                  "Scale": 1
                }
              },
              "Text": "18:50",
              "TextColours": {
                "b": 255,
                "g": 255,
                "r": 255
              },
              "VertFormatting": "CentreAligned",
              "WindowTouchThroughMode": "MousePassThroughOpen",
              "word_warpped": false
            }
          ],
          "id": {
            "value": "1bec8518-827c-4584-8c52-343a312f4d56"
          },
          "name": "CountDownLayout",
          "pos": {
            "UDim_X": {
              "Offect": -20
            }
          },
          "size": {
            "UDim_X": {
              "Offect": 130
            },
            "UDim_Y": {
              "Offect": 48
            }
          },
          "Visible": false,
          "WindowTouchThroughMode": "MousePassThroughOpen"
        },
        {
          "__OBJ_TYPE": "DefaultWindow",
          "anchor": {
            "HorizontalAlignment": "Right",
            "VerticalAlignment": "Centre"
          },
          "children": [
            {
              "__OBJ_TYPE": "StaticImage",
              "anchor": {
                "HorizontalAlignment": "Centre",
                "VerticalAlignment": "Centre"
              },
              "id": {
                "value": "475e7c3e-6363-4a3e-b57d-b631be8bb5f6"
              },
              "Image": {
                "asset": "asset/Texture/Gui/imagesets/main_ui.imageset",
                "imageset_key": "icon_coin_bg",
                "selector": "asset/Texture/Gui/imagesets/main_ui.imageset"
              },
              "name": "coinLayoutBg",
              "size": {
                "UDim_X": {
                  "Offect": 0,
                  "Scale": 1
                },
                "UDim_Y": {
                  "Offect": 0,
                  "Scale": 1
                }
              }
            },
            {
              "__OBJ_TYPE": "StaticImage",
              "anchor": {
                "VerticalAlignment": "Centre"
              },
              "id": {
                "value": "f66c0c30-025f-442a-8f08-f46c108f0de3"
              },
              "Image": {
                "asset": "asset/Texture/Gui/imagesets/main_ui.imageset",
                "imageset_key": "icon_diamond",
                "selector": "asset/Texture/Gui/imagesets/main_ui.imageset"
              },
              "name": "coinIcon",
              "pos": {
                "UDim_X": {
                  "Offect": 8
                }
              },
              "size": {
                "UDim_X": {
                  "Offect": 32
                },
                "UDim_Y": {
                  "Offect": 32
                }
              }
            },
            {
              "__OBJ_TYPE": "StaticText",
              "anchor": {
                "HorizontalAlignment": "Centre",
                "VerticalAlignment": "Centre"
              },
              "Font_size": 14,
              "HorzFormatting": "CentreAligned",
              "id": {
                "value": "1d58c87d-2371-4dba-a5b4-ba8aacc7ed3f"
              },
              "name": "coinText",
              "size": {
                "UDim_X": {
                  "Offect": 0,
                  "Scale": 0.7
                },
                "UDim_Y": {
                  "Offect": 35
                }
              },
              "Text": "300000",
              "TextColours": {
                "b": 255,
                "g": 255,
                "r": 255
              },
              "VertFormatting": "CentreAligned",
              "word_warpped": false
            },
            {
              "__OBJ_TYPE": "StaticImage",
              "anchor": {
                "HorizontalAlignment": "Right",
                "VerticalAlignment": "Centre"
              },
              "id": {
                "value": "1177afec-b753-4ade-aef4-f0712db660d3"
              },
              "Image": {
                "asset": "asset/Texture/Gui/imagesets/main_ui.imageset",
                "imageset_key": "icon_recharge_btn",
                "selector": "asset/Texture/Gui/imagesets/main_ui.imageset"
              },
              "name": "buyBtn",
              "pos": {
                "UDim_X": {
                  "Offect": 2
                }
              },
              "size": {
                "UDim_X": {
                  "Offect": 38
                },
                "UDim_Y": {
                  "Offect": 38
                }
              }
            }
          ],
          "id": {
            "value": "64bc6916-5f2a-4955-b2c1-49dca3b7188d"
          },
          "name": "BuyBtnLayout",
          "pos": {
            "UDim_X": {
              "Offect": -20
            }
          },
          "size": {
            "UDim_X": {
              "Offect": 170
            },
            "UDim_Y": {
              "Offect": 38
            }
          },
          "Visible": false,
          "WindowTouchThroughMode": "MousePassThroughOpen"
        },
        {
          "__OBJ_TYPE": "DefaultWindow",
          "children": [
            {
              "__OBJ_TYPE": "StaticImage",
              "anchor": {
                "HorizontalAlignment": "Centre"
              },
              "id": {
                "value": "618856c5-4c3d-4325-a0bb-d94c6502c625"
              },
              "Image": {
                "asset": "asset/Texture/Gui/imagesets/main_ui.imageset",
                "imageset_key": "icon_backEdit",
                "selector": "asset/Texture/Gui/imagesets/main_ui.imageset"
              },
              "name": "backEditBtn",
              "size": {
                "UDim_X": {
                  "Offect": 48
                },
                "UDim_Y": {
                  "Offect": 48
                }
              }
            },
            {
              "__OBJ_TYPE": "StaticImage",
              "anchor": {
                "HorizontalAlignment": "Centre"
              },
              "id": {
                "value": "838980e7-7d7a-4312-b622-0a2a7cfcbdca"
              },
              "Image": {
                "asset": "asset/Texture/Gui/imagesets/main_ui.imageset",
                "imageset_key": "icon_onlineGame",
                "selector": "asset/Texture/Gui/imagesets/main_ui.imageset"
              },
              "name": "onlineGameBtn",
              "pos": {
                "UDim_Y": {
                  "Offect": 60
                }
              },
              "size": {
                "UDim_X": {
                  "Offect": 48
                },
                "UDim_Y": {
                  "Offect": 48
                }
              }
            },
            {
              "__OBJ_TYPE": "StaticImage",
              "anchor": {
                "HorizontalAlignment": "Centre"
              },
              "id": {
                "value": "5f311483-3c04-45ab-acb7-f3e3716f61c7"
              },
              "Image": {
                "asset": "asset/Texture/Gui/imagesets/main_ui.imageset",
                "imageset_key": "icon_uploadGame",
                "selector": "asset/Texture/Gui/imagesets/main_ui.imageset"
              },
              "name": "uploadGameBtn",
              "pos": {
                "UDim_Y": {
                  "Offect": 121.95
                }
              },
              "size": {
                "UDim_X": {
                  "Offect": 48
                },
                "UDim_Y": {
                  "Offect": 48.0
                }
              }
            }
          ],
          "id": {
            "value": "46aef5db-4c01-460c-ac81-3b773d170cc8"
          },
          "name": "EditGameLayout",
          "pos": {
            "UDim_X": {
              "Offect": 20
            },
            "UDim_Y": {
              "Offect": 90
            }
          },
          "size": {
            "UDim_X": {
              "Offect": 50
            },
            "UDim_Y": {
              "Offect": 170
            }
          },
          "Visible": false,
          "WindowTouchThroughMode": "MousePassThroughOpen"
        },
        {
          "__OBJ_TYPE": "DefaultWindow",
          "children": [
            {
              "__OBJ_TYPE": "DefaultWindow",
              "children": [
                {
                  "__OBJ_TYPE": "StaticImage",
                  "id": {
                    "value": "1e4d688c-091b-4d43-bb17-65869bd7d5f4"
                  },
                  "Image": {
                    "asset": "asset/Texture/Gui/imagesets/main_ui.imageset",
                    "imageset_key": "icon_onlineRoom_bg",
                    "selector": "asset/Texture/Gui/imagesets/main_ui.imageset"
                  },
                  "name": "OnlineRoomLayout_Bg",
                  "pos": {
                    "UDim_X": {
                      "Offect": 5
                    }
                  },
                  "size": {
                    "UDim_X": {
                      "Offect": -5,
                      "Scale": 1
                    },
                    "UDim_Y": {
                      "Offect": 48
                    }
                  },
                  "StaticImageStretch": {
                    "bottom_left": 8,
                    "top_left": 8
                  }
                },
                {
                  "__OBJ_TYPE": "StaticImage",
                  "id": {
                    "value": "dc5dc81a-2300-4063-9a4e-06fb638ca928"
                  },
                  "Image": {
                    "asset": "asset/Texture/Gui/imagesets/main_ui.imageset",
                    "imageset_key": "icon_invite_friends",
                    "selector": "asset/Texture/Gui/imagesets/main_ui.imageset"
                  },
                  "name": "OnlineRoomLayout_Btn",
                  "size": {
                    "UDim_X": {
                      "Offect": 48
                    },
                    "UDim_Y": {
                      "Offect": 48
                    }
                  }
                },
                {
                  "__OBJ_TYPE": "StaticText",
                  "id": {
                    "value": "5a230f81-ac2a-4f16-bc04-55cd43953bde"
                  },
                  "name": "OnlineRoomLayout_tipText",
                  "pos": {
                    "UDim_X": {
                      "Offect": 52
                    },
                    "UDim_Y": {
                      "Offect": 4
                    }
                  },
                  "size": {
                    "UDim_X": {
                      "Offect": -52,
                      "Scale": 1
                    },
                    "UDim_Y": {
                      "Offect": 22
                    }
                  },
                  "Text": "房间号",
                  "TextColours": {
                    "b": 255,
                    "g": 255,
                    "r": 255
                  },
                  "word_warpped": false
                },
                {
                  "__OBJ_TYPE": "StaticText",
                  "Font_size": 14,
                  "id": {
                    "value": "c7a7cc43-9774-45d4-961e-b23f0de7efee"
                  },
                  "name": "OnlineRoomLayout_roomId",
                  "pos": {
                    "UDim_X": {
                      "Offect": 52
                    },
                    "UDim_Y": {
                      "Offect": 21
                    }
                  },
                  "size": {
                    "UDim_X": {
                      "Offect": -52,
                      "Scale": 1
                    },
                    "UDim_Y": {
                      "Offect": 29
                    }
                  },
                  "Text": "21023940",
                  "TextColours": {
                    "b": 144,
                    "g": 180,
                    "r": 219
                  },
                  "word_warpped": false
                }
              ],
              "id": {
                "value": "38c9437b-f302-412c-a24a-3bacee0280f1"
              },
              "name": "OnlineRoomLayout",
              "size": {
                "UDim_X": {
                  "Offect": 0,
                  "Scale": 1
                },
                "UDim_Y": {
                  "Offect": 48
                }
              }
            },
            {
              "__OBJ_TYPE": "StaticImage",
              "id": {
                "value": "9cb16ced-c889-4c28-b9dd-e8343556f2dc"
              },
              "Image": {
                "asset": "asset/Texture/Gui/imagesets/main_ui.imageset",
                "imageset_key": "icon_uploadGame",
                "selector": "asset/Texture/Gui/imagesets/main_ui.imageset"
              },
              "name": "onlineGameBtn_online",
              "pos": {
                "UDim_Y": {
                  "Offect": 60
                }
              },
              "size": {
                "UDim_X": {
                  "Offect": 48
                },
                "UDim_Y": {
                  "Offect": 48
                }
              },
              "Visible": false
            }
          ],
          "id": {
            "value": "d8cd7fcc-029d-411b-8f3b-9d5e97d86608"
          },
          "name": "OnlineGameLayout",
          "pos": {
            "UDim_X": {
              "Offect": 20
            },
            "UDim_Y": {
              "Offect": 90
            }
          },
          "size": {
            "UDim_X": {
              "Offect": 160
            },
            "UDim_Y": {
              "Offect": 120
            }
          },
          "Visible": false,
          "WindowTouchThroughMode": "MousePassThroughOpen"
        },
        {
          "__OBJ_TYPE": "DefaultWindow",
          "anchor": {
            "HorizontalAlignment": "Centre",
            "VerticalAlignment": "Centre"
          },
          "children": [
            {
              "__OBJ_TYPE": "StaticImage",
              "Alpha": 0.5,
              "BackgroundColours": {
                "b": 0,
                "g": 0,
                "r": 0
              },
              "BackgroundEnabled": true,
              "id": {
                "value": "edd97f4a-c320-43b9-b83b-d87751466495"
              },
              "Image": {
                "asset": "",
                "selector": ""
              },
              "name": "gameInfoBg",
              "size": {
                "UDim_X": {
                  "Offect": 0,
                  "Scale": 1
                },
                "UDim_Y": {
                  "Offect": 0,
                  "Scale": 1
                }
              },
              "WindowTouchThroughMode": "MousePassThroughOpen"
            },
            {
              "__OBJ_TYPE": "StaticText",
              "Font_size": 14,
              "HorzFormatting": "CentreAligned",
              "id": {
                "value": "65083b4e-0b5a-492f-8984-42824088a80a"
              },
              "name": "playerCountText",
              "size": {
                "UDim_X": {
                  "Offect": 0,
                  "Scale": 0.5
                },
                "UDim_Y": {
                  "Offect": 0,
                  "Scale": 1
                }
              },
              "Text": "总人数：1/20",
              "TextColours": {
                "b": 255,
                "g": 255,
                "r": 255
              },
              "VertFormatting": "CentreAligned",
              "WindowTouchThroughMode": "MousePassThroughOpen",
              "word_warpped": false
            },
            {
              "__OBJ_TYPE": "StaticText",
              "Font_size": 14,
              "HorzFormatting": "CentreAligned",
              "id": {
                "value": "550b424a-c4c7-4c46-a634-278579e31d1e"
              },
              "name": "scoreText",
              "pos": {
                "UDim_X": {
                  "Scale": 0.5
                }
              },
              "size": {
                "UDim_X": {
                  "Offect": 0,
                  "Scale": 0.5
                },
                "UDim_Y": {
                  "Offect": 0,
                  "Scale": 1
                }
              },
              "Text": "分数: 300",
              "TextColours": {
                "b": 255,
                "g": 255,
                "r": 255
              },
              "VertFormatting": "CentreAligned",
              "WindowTouchThroughMode": "MousePassThroughOpen",
              "word_warpped": false
            }
          ],
          "id": {
            "value": "2768186f-b246-4d15-afb0-ca9ed4bb358e"
          },
          "name": "SingleGameInfoLayout",
          "pos": {
            "UDim_X": {
              "Offect": -30
            }
          },
          "size": {
            "UDim_Y": {
              "Offect": 48
            }
          },
          "Visible": false,
          "WindowTouchThroughMode": "MousePassThroughOpen"
        },
        {
          "__OBJ_TYPE": "DefaultWindow",
          "anchor": {
            "HorizontalAlignment": "Centre"
          },
          "children": [
            {
              "__OBJ_TYPE": "StaticText",
              "BorderColor": {
                "b": 67,
                "g": 59,
                "r": 42
              },
              "BorderWidth": 5,
              "Font_size": 34,
              "HorzFormatting": "CentreAligned",
              "id": {
                "value": "cfb401a2-c84c-4779-affe-07146cb94253"
              },
              "name": "CountDownText_Tip",
              "size": {
                "UDim_X": {
                  "Offect": 0,
                  "Scale": 1
                },
                "UDim_Y": {
                  "Offect": 60
                }
              },
              "Text": "计入红队倒计时",
              "TextColours": {
                "b": 255,
                "g": 255,
                "r": 255
              },
              "VertFormatting": "CentreAligned",
              "WindowTouchThroughMode": "MousePassThroughOpen",
              "word_warpped": false
            },
            {
              "__OBJ_TYPE": "StaticText",
              "anchor": {
                "HorizontalAlignment": "Centre"
              },
              "BorderColor": {
                "b": 67,
                "g": 59,
                "r": 42
              },
              "BorderWidth": 5,
              "Font": "BungeeRegular",
              "Font_size": 70,
              "HorzFormatting": "CentreAligned",
              "id": {
                "value": "1c3121e2-1004-4e2f-8468-e5151f742cd4"
              },
              "name": "CountDownText_Num",
              "pos": {
                "UDim_X": {
                  "Offect": -6
                },
                "UDim_Y": {
                  "Offect": 70
                }
              },
              "size": {
                "UDim_X": {
                  "Offect": 206
                },
                "UDim_Y": {
                  "Offect": 110
                }
              },
              "Text": "15",
              "TextColours": {
                "b": 255,
                "g": 255,
                "r": 255
              },
              "WindowTouchThroughMode": "MousePassThroughOpen",
              "word_warpped": false
            }
          ],
          "id": {
            "value": "7da7cc57-2ba9-455b-8f49-6f8834ef3b24"
          },
          "name": "PropCountDownLayout",
          "pos": {
            "UDim_Y": {
              "Offect": 30
            }
          },
          "size": {
            "UDim_X": {
              "Offect": 650
            },
            "UDim_Y": {
              "Offect": 275
            }
          },
          "Visible": false,
          "WindowTouchThroughMode": "MousePassThroughOpen"
        }
      ],
      "id": {
        "value": "81d56a91-5ee8-4b20-9995-b26d42c1e2f1"
      },
      "size": {
        "UDim_X": {
          "Offect": 0,
          "Scale": 1
        },
        "UDim_Y": {
          "Offect": 58
        }
      },
      "WindowTouchThroughMode": "MousePassThroughOpen"
    }
  },
  "meta": {
    "EXPORT": {
      "layout": "57dc41a2e9a8edb5a62db77d47f4116e",
      "triggers.bts": "d1fd7037f4941cd1b8cbfb94bb926990"
    },
    "VERSION": "0.22"
  }
}