{
  "data": {
    "triggers": {
      "list": [
        {
          "actions": [
            {
              "__OBJ_TYPE": "Action_KillEntity",
              "components": [
                {
                  "__OBJ_TYPE": "Component_Params",
                  "params": [
                    {
                      "value": {
                        "__OBJ_TYPE": "T_Entity",
                        "action": "59a49df3-fe0d-4358-b261-3e309eb07cae"
                      }
                    },
                    {
                      "value": {
                        "__OBJ_TYPE": "T_Entity"
                      }
                    }
                  ]
                }
              ],
              "id": {
                "value": "07c2b1ae-e409-4ed5-aa78-99d69ed4e656"
              },
              "pos": {
                "x": 723,
                "y": 295.5
              }
            },
            {
              "__OBJ_TYPE": "Action_GetContextVar",
              "components": [
                {
                  "__OBJ_TYPE": "Component_Context",
                  "key": "obj2"
                }
              ],
              "id": {
                "value": "59a49df3-fe0d-4358-b261-3e309eb07cae"
              },
              "pos": {
                "x": 1081,
                "y": 372.5
              },
              "type": "T_Entity"
            }
          ],
          "root": {
            "components": [
              {
                "__OBJ_TYPE": "Component_Sequence",
                "children": [
                  {
                    "action": "07c2b1ae-e409-4ed5-aa78-99d69ed4e656"
                  }
                ]
              }
            ],
            "id": {
              "value": "f11a277e-78fb-46f9-80ba-a8e633896399"
            }
          },
          "type": "Trigger_PartTouchEntityBegin"
        }
      ]
    }
  },
  "meta": {
    "EXPORT": {
      "triggers.bts": "2a66487b7194814eef54159c357806a2"
    },
    "VERSION": "0.20"
  }
}