{
  "data": {
    "triggers": {
      "list": [
        {
          "actions": [
            {
              "__OBJ_TYPE": "Action_SetEntityPosition",
              "components": [
                {
                  "__OBJ_TYPE": "Component_Params",
                  "params": [
                    {
                      "value": {
                        "__OBJ_TYPE": "T_Entity",
                        "action": "b9fc1537-b83a-4966-bf43-255387bdb048"
                      }
                    },
                    {
                      "must": false,
                      "value": {
                        "__OBJ_TYPE": "T_Map",
                        "rawval": "speed16"
                      }
                    },
                    {
                      "value": {
                        "__OBJ_TYPE": "T_ScenePos",
                        "rawval": {
                          "pos": {
                            "y": 5
                          }
                        }
                      }
                    },
                    {
                      "value": {
                        "__OBJ_TYPE": "T_Int"
                      }
                    },
                    {
                      "value": {
                        "__OBJ_TYPE": "T_Int"
                      }
                    }
                  ]
                }
              ],
              "id": {
                "value": "949591f8-501a-4ad2-b118-cf7ee47cb2cc"
              },
              "pos": {
                "x": 747,
                "y": 136
              }
            },
            {
              "__OBJ_TYPE": "Action_GetContextVar",
              "components": [
                {
                  "__OBJ_TYPE": "Component_Context",
                  "key": "obj1"
                }
              ],
              "id": {
                "value": "b9fc1537-b83a-4966-bf43-255387bdb048"
              },
              "pos": {
                "x": 1345,
                "y": 204
              },
              "type": "T_Entity"
            },
            {
              "__OBJ_TYPE": "Action_SetEntityRebirthPosition",
              "components": [
                {
                  "__OBJ_TYPE": "Component_Params",
                  "params": [
                    {
                      "value": {
                        "__OBJ_TYPE": "T_Entity",
                        "action": "a9e2a70e-0861-4bea-9583-8d64b58eecec"
                      }
                    },
                    {
                      "value": {
                        "__OBJ_TYPE": "T_MapObj",
                        "action": "883845a7-57ed-499d-b12a-f580498c3a93"
                      }
                    },
                    {
                      "value": {
                        "__OBJ_TYPE": "T_ScenePos",
                        "rawval": {
                          "pos": {
                            "y": 5
                          }
                        }
                      }
                    }
                  ]
                }
              ],
              "id": {
                "value": "09ca98f9-8c8d-4492-a51f-08c3a491ee50"
              },
              "pos": {
                "x": 692,
                "y": 471
              }
            },
            {
              "__OBJ_TYPE": "Action_GetContextVar",
              "components": [
                {
                  "__OBJ_TYPE": "Component_Context",
                  "key": "obj1"
                }
              ],
              "id": {
                "value": "a9e2a70e-0861-4bea-9583-8d64b58eecec"
              },
              "pos": {
                "x": 1326,
                "y": 390
              },
              "type": "T_Entity"
            },
            {
              "__OBJ_TYPE": "GetStaticMap",
              "components": [
                {
                  "__OBJ_TYPE": "Component_Params",
                  "params": [
                    {
                      "value": {
                        "__OBJ_TYPE": "T_Map",
                        "rawval": "speed16"
                      }
                    },
                    {
                      "value": {
                        "__OBJ_TYPE": "T_Bool"
                      }
                    }
                  ]
                }
              ],
              "id": {
                "value": "883845a7-57ed-499d-b12a-f580498c3a93"
              },
              "pos": {
                "x": 1340,
                "y": 584
              }
            }
          ],
          "custom_trigger_data": {
            "name": {
              "value": "e7cb8ba6-c182-4269-a1dd-3d06be48d46b"
            }
          },
          "root": {
            "components": [
              {
                "__OBJ_TYPE": "Component_Sequence",
                "children": [
                  {
                    "action": "949591f8-501a-4ad2-b118-cf7ee47cb2cc"
                  },
                  {
                    "action": "09ca98f9-8c8d-4492-a51f-08c3a491ee50"
                  }
                ]
              }
            ],
            "id": {
              "value": "7b77b26e-f136-472b-a902-d289e95c0171"
            }
          },
          "type": "Trigger_RegionEnter"
        }
      ]
    }
  },
  "meta": {
    "EXPORT": {
      "setting.json": "ca786449e6a47060c8038f6e643bece9",
      "triggers.bts": "bd627e78408e4bf537cc7b7fd1ffe077"
    },
    "VERSION": "0.21"
  }
}