{
  "data": {
    "triggers": {
      "list": [
        {
          "actions": [
            {
              "__OBJ_TYPE": "Action_KillEntity",
              "components": [
                {
                  "__OBJ_TYPE": "Component_Params",
                  "params": [
                    {
                      "value": {
                        "__OBJ_TYPE": "T_Entity",
                        "action": "31682727-33c3-4429-9a4c-c7badeee138f"
                      }
                    },
                    {
                      "value": {
                        "__OBJ_TYPE": "T_Entity"
                      }
                    }
                  ]
                }
              ],
              "id": {
                "value": "ec2d21e7-207e-4bdb-a00e-a613b83b1865"
              },
              "pos": {
                "x": 648,
                "y": 331.5
              }
            },
            {
              "__OBJ_TYPE": "Action_GetContextVar",
              "components": [
                {
                  "__OBJ_TYPE": "Component_Context",
                  "key": "obj2"
                }
              ],
              "id": {
                "value": "31682727-33c3-4429-9a4c-c7badeee138f"
              },
              "pos": {
                "x": 1006,
                "y": 408.5
              },
              "type": "T_Entity"
            }
          ],
          "root": {
            "components": [
              {
                "__OBJ_TYPE": "Component_Sequence",
                "children": [
                  {
                    "action": "ec2d21e7-207e-4bdb-a00e-a613b83b1865"
                  }
                ]
              }
            ],
            "id": {
              "value": "2f635552-6639-4ab9-853c-fae514d780ad"
            }
          },
          "type": "Trigger_PartTouchEntityBegin"
        }
      ]
    }
  },
  "meta": {
    "EXPORT": {
      "triggers.bts": "2a66487b7194814eef54159c357806a2"
    },
    "VERSION": "0.20"
  }
}